librelingo_utils/__init__.py
librelingo_utils/utils.py
librelingo_utils-2.6.2.dist-info/WHEEL
librelingo_utils-2.6.2.dist-info/METADATA
librelingo_utils-2.6.2.dist-info/RECORD
