Metadata-Version: 2.1
Name: librelingo-utils
Version: 2.6.2
Summary: Utilities to be used in LibreLingo-related-packages
License: AGPLv3
Author: Dániel Kántor
Author-email: git@daniel-kantor.com
Requires-Python: >=3.8,<4.0
Classifier: License :: Other/Proprietary License
Classifier: Programming Language :: Python :: 3
Classifier: Programming Language :: Python :: 3.8
Classifier: Programming Language :: Python :: 3.9
Classifier: Programming Language :: Python :: 3.10
Classifier: Programming Language :: Python :: 3.11
Requires-Dist: librelingo-types (>=3.0.0,<4.0.0)
Requires-Dist: regex (>=2022.0.0,<2023.0.0)
